{
  "mappings": {
    "_meta": {
      "description": "Semantic memory index for DevOps teams. Stores structured organizational knowledge as entity-attribute-value (SPO triples). Example: entity=payment-service, attribute=db-connection-pool-size, value=50. The content field enables natural language semantic search, while entity/attribute fields enable exact keyword search."
    },
    "properties": {
      "content":       { "type": "semantic_text", "inference_id": ".elser-2-elastic" },
      "entity":        { "type": "keyword" },
      "attribute":     { "type": "keyword" },
      "value":         { "type": "text", "fields": { "keyword": { "type": "keyword" } } },
      "confidence":    { "type": "float" },
      "category":      { "type": "keyword" },
      "source_conversation_ids": { "type": "keyword" },
      "first_observed": { "type": "date" },
      "last_updated":   { "type": "date" },
      "update_count":   { "type": "integer", "null_value": 1 },
      "external_refs":  { "type": "keyword" }
    }
  }
}
